Basic/TEST/and_gate.vhd
library ieee;
use ieee.std_logic_1164.all;

entity and_gate is
    port (
        A : in std_logic;
        B : in std_logic;
        Y : out std_logic
    );
end entity;

-- architecture behavior of and_gate is
-- begin
    -- normal instant connection
    -- Y <= A and B;
-- end architecture;
architecture behavior of and_gate is
begin
    -- add 2 ns delay to output
    Y <= A and B after 2 ns;
end architecture;

Basic/TEST/tb_and_gate.vhd
library ieee;
use ieee.std_logic_1164.all;

entity tb_and_gate is
end entity;

architecture test of tb_and_gate is
    signal A, B, Y : std_logic;
begin
    uut: entity work.and_gate
        port map (
            A => A,
            B => B,
            Y => Y
        );

    -- test sequence
    process
    begin
        A <= '0'; B <= '0'; wait for 10 ns;
        A <= '0'; B <= '1'; wait for 10 ns;
        A <= '1'; B <= '0'; wait for 10 ns;
        A <= '1'; B <= '1'; wait for 10 ns;
        wait;
    end process;
end architecture;

Basic/TEST/wave.vcd
$date
  Tue Oct 28 08:56:47 2025
$end
$version
  GHDL v0
$end
$timescale
  1 fs
$end
$scope module standard $end
$upscope $end
$scope module std_logic_1164 $end
$upscope $end
$scope module tb_and_gate $end
$var reg 1 ! a $end
$var reg 1 " b $end
$var reg 1 # y $end
$scope module uut $end
$var reg 1 $ a $end
$var reg 1 % b $end
$var reg 1 & y $end
$upscope $end
$upscope $end
$enddefinitions $end
#0
0!
0"
U#
0$
0%
U&
#2000000
0#
0&
#10000000
1"
1%
#12000000
0&
#20000000
1!
0"
1$
0%
#22000000
0&
#30000000
1"
1%
#32000000
1#
1&
