Advance/4-1_MUX/mux.vhd
library ieee;
use ieee.std_logic_1164.all;

entity cmux is
  port(
    s0 : in std_logic;
    s1 : in std_logic;
    x1,x2,x3,x4 : in std_logic;
    y : out std_logic
  );
end entity;

architecture logic of cmux is
  begin
    y <= (not s0 and not s1 and x1) or (not s0 and s1 and x2) or (s0 and not s1 and x3) or (s0 and s1 and x4);
end architecture;

Advance/4-1_MUX/tb_mux.vhd
library ieee;
use ieee.std_logic_1164.all;

entity tb_cmux is
end entity;

architecture test of tb_cmux is 
	signal S0,S1,X1,X2,X3,X4,Y : std_logic ;
	begin 
		uut : entity work.cmux
			port map(
				s0 => S0,
				s1 => S1,
				x1 => X1,
				x2 => X2,
				x3 => X3,
				x4 => X4,
				y => Y
			);
		process
			begin
				---Check X1
				S0 <= '0';S1 <= '0';X1 <= '0';X2 <= '0';X3 <= '0';X4 <= '0';wait for 5 ns;
				S0 <= '0';S1 <= '0';X1 <= '1';X2 <= '0';X3 <= '0';X4 <= '0';wait for 5 ns;
				---Check X2
				S0 <= '0';S1 <= '1';X2 <= '0';X1 <= '0';X3 <= '0';X4 <= '0';wait for 5 ns;
				S0 <= '0';S1 <= '1';X2 <= '1';X1 <= '0';X3 <= '0';X4 <= '0';wait for 5 ns;
				---Check X3
				S0 <= '1';S1 <= '0';X3 <= '0';X2 <= '0';X1 <= '0';X4 <= '0';wait for 5 ns;
				S0 <= '1';S1 <= '0';X3 <= '1';X2 <= '0';X1 <= '0';X4 <= '0';wait for 5 ns;
				---Check X4
				S0 <= '1';S1 <= '1';X4 <= '0';X2 <= '0';X3 <= '0';X1 <= '0';wait for 5 ns;
				S0 <= '1';S1 <= '1';X4 <= '1';X2 <= '0';X3 <= '0';X1 <= '0';wait for 5 ns;
				wait;
		end process;
end architecture;

Advance/4-1_MUX/wave.vcd
$date
  Sun Jan 04 18:17:44 2026
$end
$version
  GHDL v0
$end
$timescale
  1 fs
$end
$scope module standard $end
$upscope $end
$scope module std_logic_1164 $end
$upscope $end
$scope module tb_cmux $end
$var reg 1 ! s0 $end
$var reg 1 " s1 $end
$var reg 1 # x1 $end
$var reg 1 $ x2 $end
$var reg 1 % x3 $end
$var reg 1 & x4 $end
$var reg 1 ' y $end
$scope module uut $end
$var reg 1 ( s0 $end
$var reg 1 ) s1 $end
$var reg 1 * x1 $end
$var reg 1 + x2 $end
$var reg 1 , x3 $end
$var reg 1 - x4 $end
$var reg 1 . y $end
$upscope $end
$upscope $end
$enddefinitions $end
#0
0!
0"
0#
0$
0%
0&
0'
0(
0)
0*
0+
0,
0-
0.
#5000000
1#
1'
1*
1.
#10000000
1"
0#
0'
1)
0*
0.
#15000000
1$
1'
1+
1.
#20000000
1!
0"
0$
0'
1(
0)
0+
0.
#25000000
1%
1'
1,
1.
#30000000
1"
0%
0'
1)
0,
0.
#35000000
1&
1'
1-
1.
